{"stats":{"original_rows":50,"final_rows":50,"columns_detected":5,"duplicates_removed":0},"columns":["Invoice Number","Date","Client","Total Amount","Status"],"preview":[{"Invoice Number":"INV-0001","Date":"2023-01-01 00:00:00","Client":"Client A","Total Amount":4774.976634864386,"Status":"Paid"},{"Invoice Number":"INV-0002","Date":"2023-01-02 00:00:00","Client":"Client B","Total Amount":1731.304658199758,"Status":"Pending"},{"Invoice Number":"INV-0003","Date":"2023-01-03 00:00:00","Client":"Client C","Total Amount":3761.652142224968,"Status":"Overdue"},{"Invoice Number":"INV-0004","Date":"2023-01-04 00:00:00","Client":"Client A","Total Amount":4058.922111627606,"Status":"Paid"},{"Invoice Number":"INV-0005","Date":"2023-01-05 00:00:00","Client":"Client B","Total Amount":1300.116832420014,"Status":"Pending"},{"Invoice Number":"INV-0006","Date":"2023-01-06 00:00:00","Client":"Client C","Total Amount":4495.008791014383,"Status":"Overdue"},{"Invoice Number":"INV-0007","Date":"2023-01-07 00:00:00","Client":"Client A","Total Amount":1748.106150623818,"Status":"Paid"},{"Invoice Number":"INV-0008","Date":"2023-01-08 00:00:00","Client":"Client B","Total Amount":2672.931664782349,"Status":"Pending"},{"Invoice Number":"INV-0009","Date":"2023-01-09 00:00:00","Client":"Client C","Total Amount":4996.918259706255,"Status":"Overdue"},{"Invoice Number":"INV-0010","Date":"2023-01-10 00:00:00","Client":"Client A","Total Amount":4871.498761014725,"Status":"Paid"},{"Invoice Number":"INV-0011","Date":"2023-01-11 00:00:00","Client":"Client B","Total Amount":1949.67990464144,"Status":"Pending"},{"Invoice Number":"INV-0012","Date":"2023-01-12 00:00:00","Client":"Client C","Total Amount":1997.663286241917,"Status":"Overdue"},{"Invoice Number":"INV-0013","Date":"2023-01-13 00:00:00","Client":"Client A","Total Amount":919.455427503797,"Status":"Paid"},{"Invoice Number":"INV-0014","Date":"2023-01-14 00:00:00","Client":"Client B","Total Amount":1191.52116779265,"Status":"Pending"},{"Invoice Number":"INV-0015","Date":"2023-01-15 00:00:00","Client":"Client C","Total Amount":3242.83800607758,"Status":"Overdue"},{"Invoice Number":"INV-0016","Date":"2023-01-16 00:00:00","Client":"Client A","Total Amount":1734.627731119536,"Status":"Paid"},{"Invoice Number":"INV-0017","Date":"2023-01-17 00:00:00","Client":"Client B","Total Amount":4748.34461792154,"Status":"Pending"},{"Invoice Number":"INV-0018","Date":"2023-01-18 00:00:00","Client":"Client C","Total Amount":2583.286402519017,"Status":"Overdue"},{"Invoice Number":"INV-0019","Date":"2023-01-19 00:00:00","Client":"Client A","Total Amount":2335.302076217469,"Status":"Paid"},{"Invoice Number":"INV-0020","Date":"2023-01-20 00:00:00","Client":"Client B","Total Amount":4923.025419601991,"Status":"Pending"},{"Invoice Number":"INV-0021","Date":"2023-01-21 00:00:00","Client":"Client C","Total Amount":4936.605707002811,"Status":"Overdue"},{"Invoice Number":"INV-0022","Date":"2023-01-22 00:00:00","Client":"Client A","Total Amount":2437.907447039511,"Status":"Paid"},{"Invoice Number":"INV-0023","Date":"2023-01-23 00:00:00","Client":"Client B","Total Amount":3013.265062388198,"Status":"Pending"},{"Invoice Number":"INV-0024","Date":"2023-01-24 00:00:00","Client":"Client C","Total Amount":2826.738311734759,"Status":"Overdue"},{"Invoice Number":"INV-0025","Date":"2023-01-25 00:00:00","Client":"Client A","Total Amount":3242.004793710263,"Status":"Paid"},{"Invoice Number":"INV-0026","Date":"2023-01-26 00:00:00","Client":"Client B","Total Amount":3589.621400407419,"Status":"Pending"},{"Invoice Number":"INV-0027","Date":"2023-01-27 00:00:00","Client":"Client C","Total Amount":2809.342168762387,"Status":"Overdue"},{"Invoice Number":"INV-0028","Date":"2023-01-28 00:00:00","Client":"Client A","Total Amount":1864.392520492253,"Status":"Paid"},{"Invoice Number":"INV-0029","Date":"2023-01-29 00:00:00","Client":"Client B","Total Amount":3913.501361132845,"Status":"Pending"},{"Invoice Number":"INV-0030","Date":"2023-01-30 00:00:00","Client":"Client C","Total Amount":4523.409070919635,"Status":"Overdue"},{"Invoice Number":"INV-0031","Date":"2023-01-31 00:00:00","Client":"Client A","Total Amount":2476.762315305465,"Status":"Paid"},{"Invoice Number":"INV-0032","Date":"2023-02-01 00:00:00","Client":"Client B","Total Amount":1686.745267229054,"Status":"Pending"},{"Invoice Number":"INV-0033","Date":"2023-02-02 00:00:00","Client":"Client C","Total Amount":3212.408290093727,"Status":"Overdue"},{"Invoice Number":"INV-0034","Date":"2023-02-03 00:00:00","Client":"Client A","Total Amount":1291.460750841841,"Status":"Paid"},{"Invoice Number":"INV-0035","Date":"2023-02-04 00:00:00","Client":"Client B","Total Amount":3735.67337186486,"Status":"Pending"},{"Invoice Number":"INV-0036","Date":"2023-02-05 00:00:00","Client":"Client C","Total Amount":4680.029314005316,"Status":"Overdue"},{"Invoice Number":"INV-0037","Date":"2023-02-06 00:00:00","Client":"Client A","Total Amount":1962.74141101207,"Status":"Paid"},{"Invoice Number":"INV-0038","Date":"2023-02-07 00:00:00","Client":"Client B","Total Amount":4710.681864108657,"Status":"Pending"},{"Invoice Number":"INV-0039","Date":"2023-02-08 00:00:00","Client":"Client C","Total Amount":3734.40925622438,"Status":"Overdue"},{"Invoice Number":"INV-0040","Date":"2023-02-09 00:00:00","Client":"Client A","Total Amount":2614.839971944059,"Status":"Paid"},{"Invoice Number":"INV-0041","Date":"2023-02-10 00:00:00","Client":"Client B","Total Amount":2596.911755541142,"Status":"Pending"},{"Invoice Number":"INV-0042","Date":"2023-02-11 00:00:00","Client":"Client C","Total Amount":2009.83241213913,"Status":"Overdue"},{"Invoice Number":"INV-0043","Date":"2023-02-12 00:00:00","Client":"Client A","Total Amount":2671.932159274758,"Status":"Paid"},{"Invoice Number":"INV-0044","Date":"2023-02-13 00:00:00","Client":"Client B","Total Amount":3980.605626304672,"Status":"Pending"},{"Invoice Number":"INV-0045","Date":"2023-02-14 00:00:00","Client":"Client C","Total Amount":1734.657252685092,"Status":"Overdue"},{"Invoice Number":"INV-0046","Date":"2023-02-15 00:00:00","Client":"Client A","Total Amount":4544.000303917879,"Status":"Paid"},{"Invoice Number":"INV-0047","Date":"2023-02-16 00:00:00","Client":"Client B","Total Amount":1530.345366328124,"Status":"Pending"},{"Invoice Number":"INV-0048","Date":"2023-02-17 00:00:00","Client":"Client C","Total Amount":1525.698965765268,"Status":"Overdue"},{"Invoice Number":"INV-0049","Date":"2023-02-18 00:00:00","Client":"Client A","Total Amount":4906.390990779528,"Status":"Paid"},{"Invoice Number":"INV-0050","Date":"2023-02-19 00:00:00","Client":"Client B","Total Amount":2648.980660545379,"Status":"Pending"}],"duplicates":[],"csv_download":"Invoice Number,Date,Client,Total Amount,Status\nINV-0001,2023-01-01,Client A,4774.976634864386,Paid\nINV-0002,2023-01-02,Client B,1731.304658199758,Pending\nINV-0003,2023-01-03,Client C,3761.652142224968,Overdue\nINV-0004,2023-01-04,Client A,4058.922111627606,Paid\nINV-0005,2023-01-05,Client B,1300.116832420014,Pending\nINV-0006,2023-01-06,Client C,4495.008791014383,Overdue\nINV-0007,2023-01-07,Client A,1748.106150623818,Paid\nINV-0008,2023-01-08,Client B,2672.931664782349,Pending\nINV-0009,2023-01-09,Client C,4996.918259706255,Overdue\nINV-0010,2023-01-10,Client A,4871.498761014725,Paid\nINV-0011,2023-01-11,Client B,1949.67990464144,Pending\nINV-0012,2023-01-12,Client C,1997.663286241917,Overdue\nINV-0013,2023-01-13,Client A,919.455427503797,Paid\nINV-0014,2023-01-14,Client B,1191.52116779265,Pending\nINV-0015,2023-01-15,Client C,3242.83800607758,Overdue\nINV-0016,2023-01-16,Client A,1734.627731119536,Paid\nINV-0017,2023-01-17,Client B,4748.34461792154,Pending\nINV-0018,2023-01-18,Client C,2583.286402519017,Overdue\nINV-0019,2023-01-19,Client A,2335.302076217469,Paid\nINV-0020,2023-01-20,Client B,4923.025419601991,Pending\nINV-0021,2023-01-21,Client C,4936.605707002811,Overdue\nINV-0022,2023-01-22,Client A,2437.907447039511,Paid\nINV-0023,2023-01-23,Client B,3013.265062388198,Pending\nINV-0024,2023-01-24,Client C,2826.738311734759,Overdue\nINV-0025,2023-01-25,Client A,3242.004793710263,Paid\nINV-0026,2023-01-26,Client B,3589.621400407419,Pending\nINV-0027,2023-01-27,Client C,2809.342168762387,Overdue\nINV-0028,2023-01-28,Client A,1864.392520492253,Paid\nINV-0029,2023-01-29,Client B,3913.501361132845,Pending\nINV-0030,2023-01-30,Client C,4523.409070919635,Overdue\nINV-0031,2023-01-31,Client A,2476.762315305465,Paid\nINV-0032,2023-02-01,Client B,1686.745267229054,Pending\nINV-0033,2023-02-02,Client C,3212.408290093727,Overdue\nINV-0034,2023-02-03,Client A,1291.460750841841,Paid\nINV-0035,2023-02-04,Client B,3735.67337186486,Pending\nINV-0036,2023-02-05,Client C,4680.029314005316,Overdue\nINV-0037,2023-02-06,Client A,1962.74141101207,Paid\nINV-0038,2023-02-07,Client B,4710.681864108657,Pending\nINV-0039,2023-02-08,Client C,3734.40925622438,Overdue\nINV-0040,2023-02-09,Client A,2614.839971944059,Paid\nINV-0041,2023-02-10,Client B,2596.911755541142,Pending\nINV-0042,2023-02-11,Client C,2009.83241213913,Overdue\nINV-0043,2023-02-12,Client A,2671.932159274758,Paid\nINV-0044,2023-02-13,Client B,3980.605626304672,Pending\nINV-0045,2023-02-14,Client C,1734.657252685092,Overdue\nINV-0046,2023-02-15,Client A,4544.000303917879,Paid\nINV-0047,2023-02-16,Client B,1530.345366328124,Pending\nINV-0048,2023-02-17,Client C,1525.698965765268,Overdue\nINV-0049,2023-02-18,Client A,4906.390990779528,Paid\nINV-0050,2023-02-19,Client B,2648.980660545379,Pending\n"}